src/led_test.v
module led_test (clk,rst_n,led);
input clk,rst_n;
output reg [3:0] led;
reg [7:0] timer;
always @(posedge clk or negedge rst_n)
begin
if(rst_n==1'b0)
timer<=8'd0;
else if (timer==8'd199)
timer<=8'd0;
else
timer<=timer+8'd1;
end

always @(posedge clk or negedge rst_n)
begin
if(rst_n==1'b0)
led<=4'b0000;
else if(timer==8'd49)
led<=4'b0001;
else if(timer==8'd99)
led<=4'b0010;
else if(timer==8'd149)
led<=4'b0100;
else if(timer==8'd199)
led<=4'b1000;
end

endmodule

tb/testbench_led_test.v
`timescale 1ns/1ps;
module testbench_led_test;
reg clk,rst_n;
wire [3:0] led;

led_test u_led_test(.clk(clk),.rst_n(rst_n),.led(led));
initial begin
    clk=0;
    forever #1 clk=~clk;
end

initial begin
    $dumpfile("wave.vcd");
    $dumpvars(0,testbench_led_test);
    rst_n=1;#8.5;
    rst_n=0;#2;
    rst_n=1;#800;
    $finish;
end
endmodule

wave.vcd
$date
	Wed Mar 25 16:01:30 2026
$end
$version
	Icarus Verilog
$end
$timescale
	1ps
$end
$scope module testbench_led_test $end
$var wire 4 ! led [3:0] $end
$var reg 1 " clk $end
$var reg 1 # rst_n $end
$scope module u_led_test $end
$var wire 1 " clk $end
$var wire 1 # rst_n $end
$var reg 4 $ led [3:0] $end
$var reg 8 % timer [7:0] $end
$upscope $end
$upscope $end
$enddefinitions $end
$comment Show the parameter values. $end
$dumpall
$end
#0
$dumpvars
bx %
bx $
1#
0"
bx !
$end
#1000
1"
#2000
0"
#3000
1"
#4000
0"
#5000
1"
#6000
0"
#7000
1"
#8000
0"
#8500
b0 %
b0 !
b0 $
0#
#9000
1"
#10000
0"
#10500
1#
#11000
b1 %
1"
#12000
0"
#13000
b10 %
1"
#14000
0"
#15000
b11 %
1"
#16000
0"
#17000
b100 %
1"
#18000
0"
#19000
b101 %
1"
#20000
0"
#21000
b110 %
1"
#22000
0"
#23000
b111 %
1"
#24000
0"
#25000
b1000 %
1"
#26000
0"
#27000
b1001 %
1"
#28000
0"
#29000
b1010 %
1"
#30000
0"
#31000
b1011 %
1"
#32000
0"
#33000
b1100 %
1"
#34000
0"
#35000
b1101 %
1"
#36000
0"
#37000
b1110 %
1"
#38000
0"
#39000
b1111 %
1"
#40000
0"
#41000
b10000 %
1"
#42000
0"
#43000
b10001 %
1"
#44000
0"
#45000
b10010 %
1"
#46000
0"
#47000
b10011 %
1"
#48000
0"
#49000
b10100 %
1"
#50000
0"
#51000
b10101 %
1"
#52000
0"
#53000
b10110 %
1"
#54000
0"
#55000
b10111 %
1"
#56000
0"
#57000
b11000 %
1"
#58000
0"
#59000
b11001 %
1"
#60000
0"
#61000
b11010 %
1"
#62000
0"
#63000
b11011 %
1"
#64000
0"
#65000
b11100 %
1"
#66000
0"
#67000
b11101 %
1"
#68000
0"
#69000
b11110 %
1"
#70000
0"
#71000
b11111 %
1"
#72000
0"
#73000
b100000 %
1"
#74000
0"
#75000
b100001 %
1"
#76000
0"
#77000
b100010 %
1"
#78000
0"
#79000
b100011 %
1"
#80000
0"
#81000
b100100 %
1"
#82000
0"
#83000
b100101 %
1"
#84000
0"
#85000
b100110 %
1"
#86000
0"
#87000
b100111 %
1"
#88000
0"
#89000
b101000 %
1"
#90000
0"
#91000
b101001 %
1"
#92000
0"
#93000
b101010 %
1"
#94000
0"
#95000
b101011 %
1"
#96000
0"
#97000
b101100 %
1"
#98000
0"
#99000
b101101 %
1"
#100000
0"
#101000
b101110 %
1"
#102000
0"
#103000
b101111 %
1"
#104000
0"
#105000
b110000 %
1"
#106000
0"
#107000
b110001 %
1"
#108000
0"
#109000
b1 !
b1 $
b110010 %
1"
#110000
0"
#111000
b110011 %
1"
#112000
0"
#113000
b110100 %
1"
#114000
0"
#115000
b110101 %
1"
#116000
0"
#117000
b110110 %
1"
#118000
0"
#119000
b110111 %
1"
#120000
0"
#121000
b111000 %
1"
#122000
0"
#123000
b111001 %
1"
#124000
0"
#125000
b111010 %
1"
#126000
0"
#127000
b111011 %
1"
#128000
0"
#129000
b111100 %
1"
#130000
0"
#131000
b111101 %
1"
#132000
0"
#133000
b111110 %
1"
#134000
0"
#135000
b111111 %
1"
#136000
0"
#137000
b1000000 %
1"
#138000
0"
#139000
b1000001 %
1"
#140000
0"
#141000
b1000010 %
1"
#142000
0"
#143000
b1000011 %
1"
#144000
0"
#145000
b1000100 %
1"
#146000
0"
#147000
b1000101 %
1"
#148000
0"
#149000
b1000110 %
1"
#150000
0"
#151000
b1000111 %
1"
#152000
0"
#153000
b1001000 %
1"
#154000
0"
#155000
b1001001 %
1"
#156000
0"
#157000
b1001010 %
1"
#158000
0"
#159000
b1001011 %
1"
#160000
0"
#161000
b1001100 %
1"
#162000
0"
#163000
b1001101 %
1"
#164000
0"
#165000
b1001110 %
1"
#166000
0"
#167000
b1001111 %
1"
#168000
0"
#169000
b1010000 %
1"
#170000
0"
#171000
b1010001 %
1"
#172000
0"
#173000
b1010010 %
1"
#174000
0"
#175000
b1010011 %
1"
#176000
0"
#177000
b1010100 %
1"
#178000
0"
#179000
b1010101 %
1"
#180000
0"
#181000
b1010110 %
1"
#182000
0"
#183000
b1010111 %
1"
#184000
0"
#185000
b1011000 %
1"
#186000
0"
#187000
b1011001 %
1"
#188000
0"
#189000
b1011010 %
1"
#190000
0"
#191000
b1011011 %
1"
#192000
0"
#193000
b1011100 %
1"
#194000
0"
#195000
b1011101 %
1"
#196000
0"
#197000
b1011110 %
1"
#198000
0"
#199000
b1011111 %
1"
#200000
0"
#201000
b1100000 %
1"
#202000
0"
#203000
b1100001 %
1"
#204000
0"
#205000
b1100010 %
1"
#206000
0"
#207000
b1100011 %
1"
#208000
0"
#209000
b10 !
b10 $
b1100100 %
1"
#210000
0"
#211000
b1100101 %
1"
#212000
0"
#213000
b1100110 %
1"
#214000
0"
#215000
b1100111 %
1"
#216000
0"
#217000
b1101000 %
1"
#218000
0"
#219000
b1101001 %
1"
#220000
0"
#221000
b1101010 %
1"
#222000
0"
#223000
b1101011 %
1"
#224000
0"
#225000
b1101100 %
1"
#226000
0"
#227000
b1101101 %
1"
#228000
0"
#229000
b1101110 %
1"
#230000
0"
#231000
b1101111 %
1"
#232000
0"
#233000
b1110000 %
1"
#234000
0"
#235000
b1110001 %
1"
#236000
0"
#237000
b1110010 %
1"
#238000
0"
#239000
b1110011 %
1"
#240000
0"
#241000
b1110100 %
1"
#242000
0"
#243000
b1110101 %
1"
#244000
0"
#245000
b1110110 %
1"
#246000
0"
#247000
b1110111 %
1"
#248000
0"
#249000
b1111000 %
1"
#250000
0"
#251000
b1111001 %
1"
#252000
0"
#253000
b1111010 %
1"
#254000
0"
#255000
b1111011 %
1"
#256000
0"
#257000
b1111100 %
1"
#258000
0"
#259000
b1111101 %
1"
#260000
0"
#261000
b1111110 %
1"
#262000
0"
#263000
b1111111 %
1"
#264000
0"
#265000
b10000000 %
1"
#266000
0"
#267000
b10000001 %
1"
#268000
0"
#269000
b10000010 %
1"
#270000
0"
#271000
b10000011 %
1"
#272000
0"
#273000
b10000100 %
1"
#274000
0"
#275000
b10000101 %
1"
#276000
0"
#277000
b10000110 %
1"
#278000
0"
#279000
b10000111 %
1"
#280000
0"
#281000
b10001000 %
1"
#282000
0"
#283000
b10001001 %
1"
#284000
0"
#285000
b10001010 %
1"
#286000
0"
#287000
b10001011 %
1"
#288000
0"
#289000
b10001100 %
1"
#290000
0"
#291000
b10001101 %
1"
#292000
0"
#293000
b10001110 %
1"
#294000
0"
#295000
b10001111 %
1"
#296000
0"
#297000
b10010000 %
1"
#298000
0"
#299000
b10010001 %
1"
#300000
0"
#301000
b10010010 %
1"
#302000
0"
#303000
b10010011 %
1"
#304000
0"
#305000
b10010100 %
1"
#306000
0"
#307000
b10010101 %
1"
#308000
0"
#309000
b100 !
b100 $
b10010110 %
1"
#310000
0"
#311000
b10010111 %
1"
#312000
0"
#313000
b10011000 %
1"
#314000
0"
#315000
b10011001 %
1"
#316000
0"
#317000
b10011010 %
1"
#318000
0"
#319000
b10011011 %
1"
#320000
0"
#321000
b10011100 %
1"
#322000
0"
#323000
b10011101 %
1"
#324000
0"
#325000
b10011110 %
1"
#326000
0"
#327000
b10011111 %
1"
#328000
0"
#329000
b10100000 %
1"
#330000
0"
#331000
b10100001 %
1"
#332000
0"
#333000
b10100010 %
1"
#334000
0"
#335000
b10100011 %
1"
#336000
0"
#337000
b10100100 %
1"
#338000
0"
#339000
b10100101 %
1"
#340000
0"
#341000
b10100110 %
1"
#342000
0"
#343000
b10100111 %
1"
#344000
0"
#345000
b10101000 %
1"
#346000
0"
#347000
b10101001 %
1"
#348000
0"
#349000
b10101010 %
1"
#350000
0"
#351000
b10101011 %
1"
#352000
0"
#353000
b10101100 %
1"
#354000
0"
#355000
b10101101 %
1"
#356000
0"
#357000
b10101110 %
1"
#358000
0"
#359000
b10101111 %
1"
#360000
0"
#361000
b10110000 %
1"
#362000
0"
#363000
b10110001 %
1"
#364000
0"
#365000
b10110010 %
1"
#366000
0"
#367000
b10110011 %
1"
#368000
0"
#369000
b10110100 %
1"
#370000
0"
#371000
b10110101 %
1"
#372000
0"
#373000
b10110110 %
1"
#374000
0"
#375000
b10110111 %
1"
#376000
0"
#377000
b10111000 %
1"
#378000
0"
#379000
b10111001 %
1"
#380000
0"
#381000
b10111010 %
1"
#382000
0"
#383000
b10111011 %
1"
#384000
0"
#385000
b10111100 %
1"
#386000
0"
#387000
b10111101 %
1"
#388000
0"
#389000
b10111110 %
1"
#390000
0"
#391000
b10111111 %
1"
#392000
0"
#393000
b11000000 %
1"
#394000
0"
#395000
b11000001 %
1"
#396000
0"
#397000
b11000010 %
1"
#398000
0"
#399000
b11000011 %
1"
#400000
0"
#401000
b11000100 %
1"
#402000
0"
#403000
b11000101 %
1"
#404000
0"
#405000
b11000110 %
1"
#406000
0"
#407000
b11000111 %
1"
#408000
0"
#409000
b1000 !
b1000 $
b0 %
1"
#410000
0"
#411000
b1 %
1"
#412000
0"
#413000
b10 %
1"
#414000
0"
#415000
b11 %
1"
#416000
0"
#417000
b100 %
1"
#418000
0"
#419000
b101 %
1"
#420000
0"
#421000
b110 %
1"
#422000
0"
#423000
b111 %
1"
#424000
0"
#425000
b1000 %
1"
#426000
0"
#427000
b1001 %
1"
#428000
0"
#429000
b1010 %
1"
#430000
0"
#431000
b1011 %
1"
#432000
0"
#433000
b1100 %
1"
#434000
0"
#435000
b1101 %
1"
#436000
0"
#437000
b1110 %
1"
#438000
0"
#439000
b1111 %
1"
#440000
0"
#441000
b10000 %
1"
#442000
0"
#443000
b10001 %
1"
#444000
0"
#445000
b10010 %
1"
#446000
0"
#447000
b10011 %
1"
#448000
0"
#449000
b10100 %
1"
#450000
0"
#451000
b10101 %
1"
#452000
0"
#453000
b10110 %
1"
#454000
0"
#455000
b10111 %
1"
#456000
0"
#457000
b11000 %
1"
#458000
0"
#459000
b11001 %
1"
#460000
0"
#461000
b11010 %
1"
#462000
0"
#463000
b11011 %
1"
#464000
0"
#465000
b11100 %
1"
#466000
0"
#467000
b11101 %
1"
#468000
0"
#469000
b11110 %
1"
#470000
0"
#471000
b11111 %
1"
#472000
0"
#473000
b100000 %
1"
#474000
0"
#475000
b100001 %
1"
#476000
0"
#477000
b100010 %
1"
#478000
0"
#479000
b100011 %
1"
#480000
0"
#481000
b100100 %
1"
#482000
0"
#483000
b100101 %
1"
#484000
0"
#485000
b100110 %
1"
#486000
0"
#487000
b100111 %
1"
#488000
0"
#489000
b101000 %
1"
#490000
0"
#491000
b101001 %
1"
#492000
0"
#493000
b101010 %
1"
#494000
0"
#495000
b101011 %
1"
#496000
0"
#497000
b101100 %
1"
#498000
0"
#499000
b101101 %
1"
#500000
0"
#501000
b101110 %
1"
#502000
0"
#503000
b101111 %
1"
#504000
0"
#505000
b110000 %
1"
#506000
0"
#507000
b110001 %
1"
#508000
0"
#509000
b1 !
b1 $
b110010 %
1"
#510000
0"
#511000
b110011 %
1"
#512000
0"
#513000
b110100 %
1"
#514000
0"
#515000
b110101 %
1"
#516000
0"
#517000
b110110 %
1"
#518000
0"
#519000
b110111 %
1"
#520000
0"
#521000
b111000 %
1"
#522000
0"
#523000
b111001 %
1"
#524000
0"
#525000
b111010 %
1"
#526000
0"
#527000
b111011 %
1"
#528000
0"
#529000
b111100 %
1"
#530000
0"
#531000
b111101 %
1"
#532000
0"
#533000
b111110 %
1"
#534000
0"
#535000
b111111 %
1"
#536000
0"
#537000
b1000000 %
1"
#538000
0"
#539000
b1000001 %
1"
#540000
0"
#541000
b1000010 %
1"
#542000
0"
#543000
b1000011 %
1"
#544000
0"
#545000
b1000100 %
1"
#546000
0"
#547000
b1000101 %
1"
#548000
0"
#549000
b1000110 %
1"
#550000
0"
#551000
b1000111 %
1"
#552000
0"
#553000
b1001000 %
1"
#554000
0"
#555000
b1001001 %
1"
#556000
0"
#557000
b1001010 %
1"
#558000
0"
#559000
b1001011 %
1"
#560000
0"
#561000
b1001100 %
1"
#562000
0"
#563000
b1001101 %
1"
#564000
0"
#565000
b1001110 %
1"
#566000
0"
#567000
b1001111 %
1"
#568000
0"
#569000
b1010000 %
1"
#570000
0"
#571000
b1010001 %
1"
#572000
0"
#573000
b1010010 %
1"
#574000
0"
#575000
b1010011 %
1"
#576000
0"
#577000
b1010100 %
1"
#578000
0"
#579000
b1010101 %
1"
#580000
0"
#581000
b1010110 %
1"
#582000
0"
#583000
b1010111 %
1"
#584000
0"
#585000
b1011000 %
1"
#586000
0"
#587000
b1011001 %
1"
#588000
0"
#589000
b1011010 %
1"
#590000
0"
#591000
b1011011 %
1"
#592000
0"
#593000
b1011100 %
1"
#594000
0"
#595000
b1011101 %
1"
#596000
0"
#597000
b1011110 %
1"
#598000
0"
#599000
b1011111 %
1"
#600000
0"
#601000
b1100000 %
1"
#602000
0"
#603000
b1100001 %
1"
#604000
0"
#605000
b1100010 %
1"
#606000
0"
#607000
b1100011 %
1"
#608000
0"
#609000
b10 !
b10 $
b1100100 %
1"
#610000
0"
#611000
b1100101 %
1"
#612000
0"
#613000
b1100110 %
1"
#614000
0"
#615000
b1100111 %
1"
#616000
0"
#617000
b1101000 %
1"
#618000
0"
#619000
b1101001 %
1"
#620000
0"
#621000
b1101010 %
1"
#622000
0"
#623000
b1101011 %
1"
#624000
0"
#625000
b1101100 %
1"
#626000
0"
#627000
b1101101 %
1"
#628000
0"
#629000
b1101110 %
1"
#630000
0"
#631000
b1101111 %
1"
#632000
0"
#633000
b1110000 %
1"
#634000
0"
#635000
b1110001 %
1"
#636000
0"
#637000
b1110010 %
1"
#638000
0"
#639000
b1110011 %
1"
#640000
0"
#641000
b1110100 %
1"
#642000
0"
#643000
b1110101 %
1"
#644000
0"
#645000
b1110110 %
1"
#646000
0"
#647000
b1110111 %
1"
#648000
0"
#649000
b1111000 %
1"
#650000
0"
#651000
b1111001 %
1"
#652000
0"
#653000
b1111010 %
1"
#654000
0"
#655000
b1111011 %
1"
#656000
0"
#657000
b1111100 %
1"
#658000
0"
#659000
b1111101 %
1"
#660000
0"
#661000
b1111110 %
1"
#662000
0"
#663000
b1111111 %
1"
#664000
0"
#665000
b10000000 %
1"
#666000
0"
#667000
b10000001 %
1"
#668000
0"
#669000
b10000010 %
1"
#670000
0"
#671000
b10000011 %
1"
#672000
0"
#673000
b10000100 %
1"
#674000
0"
#675000
b10000101 %
1"
#676000
0"
#677000
b10000110 %
1"
#678000
0"
#679000
b10000111 %
1"
#680000
0"
#681000
b10001000 %
1"
#682000
0"
#683000
b10001001 %
1"
#684000
0"
#685000
b10001010 %
1"
#686000
0"
#687000
b10001011 %
1"
#688000
0"
#689000
b10001100 %
1"
#690000
0"
#691000
b10001101 %
1"
#692000
0"
#693000
b10001110 %
1"
#694000
0"
#695000
b10001111 %
1"
#696000
0"
#697000
b10010000 %
1"
#698000
0"
#699000
b10010001 %
1"
#700000
0"
#701000
b10010010 %
1"
#702000
0"
#703000
b10010011 %
1"
#704000
0"
#705000
b10010100 %
1"
#706000
0"
#707000
b10010101 %
1"
#708000
0"
#709000
b100 !
b100 $
b10010110 %
1"
#710000
0"
#711000
b10010111 %
1"
#712000
0"
#713000
b10011000 %
1"
#714000
0"
#715000
b10011001 %
1"
#716000
0"
#717000
b10011010 %
1"
#718000
0"
#719000
b10011011 %
1"
#720000
0"
#721000
b10011100 %
1"
#722000
0"
#723000
b10011101 %
1"
#724000
0"
#725000
b10011110 %
1"
#726000
0"
#727000
b10011111 %
1"
#728000
0"
#729000
b10100000 %
1"
#730000
0"
#731000
b10100001 %
1"
#732000
0"
#733000
b10100010 %
1"
#734000
0"
#735000
b10100011 %
1"
#736000
0"
#737000
b10100100 %
1"
#738000
0"
#739000
b10100101 %
1"
#740000
0"
#741000
b10100110 %
1"
#742000
0"
#743000
b10100111 %
1"
#744000
0"
#745000
b10101000 %
1"
#746000
0"
#747000
b10101001 %
1"
#748000
0"
#749000
b10101010 %
1"
#750000
0"
#751000
b10101011 %
1"
#752000
0"
#753000
b10101100 %
1"
#754000
0"
#755000
b10101101 %
1"
#756000
0"
#757000
b10101110 %
1"
#758000
0"
#759000
b10101111 %
1"
#760000
0"
#761000
b10110000 %
1"
#762000
0"
#763000
b10110001 %
1"
#764000
0"
#765000
b10110010 %
1"
#766000
0"
#767000
b10110011 %
1"
#768000
0"
#769000
b10110100 %
1"
#770000
0"
#771000
b10110101 %
1"
#772000
0"
#773000
b10110110 %
1"
#774000
0"
#775000
b10110111 %
1"
#776000
0"
#777000
b10111000 %
1"
#778000
0"
#779000
b10111001 %
1"
#780000
0"
#781000
b10111010 %
1"
#782000
0"
#783000
b10111011 %
1"
#784000
0"
#785000
b10111100 %
1"
#786000
0"
#787000
b10111101 %
1"
#788000
0"
#789000
b10111110 %
1"
#790000
0"
#791000
b10111111 %
1"
#792000
0"
#793000
b11000000 %
1"
#794000
0"
#795000
b11000001 %
1"
#796000
0"
#797000
b11000010 %
1"
#798000
0"
#799000
b11000011 %
1"
#800000
0"
#801000
b11000100 %
1"
#802000
0"
#803000
b11000101 %
1"
#804000
0"
#805000
b11000110 %
1"
#806000
0"
#807000
b11000111 %
1"
#808000
0"
#809000
b1000 !
b1000 $
b0 %
1"
